[[{"id": 1, "text": "Bonjour", "lemma": "bonjour", "upos": "INTJ", "head": 0, "deprel": "root", "misc": "start_char=0|end_char=7", "ner": "S-MISC"}, {"id": 2, "text": "6", "lemma": "6", "upos": "NUM", "head": 3, "deprel": "nummod", "misc": "start_char=8|end_char=9", "ner": "O"}, {"id": 3, "text": "milliards", "lemma": "milliard", "upos": "NOUN", "feats": "Gender=Masc|Number=Plur", "head": 1, "deprel": "obl:arg", "misc": "start_char=10|end_char=19", "ner": "O"}, {"id": 4, "text": "et", "lemma": "et", "upos": "CCONJ", "head": 6, "deprel": "cc", "misc": "start_char=20|end_char=22", "ner": "O"}, {"id": 5, "text": "6", "lemma": "6", "upos": "NUM", "head": 6, "deprel": "nummod", "misc": "start_char=23|end_char=24", "ner": "O"}, {"id": 6, "text": "rebonds", "lemma": "rebond", "upos": "NOUN", "feats": "Gender=Masc|Number=Plur", "head": 3, "deprel": "conj", "misc": "start_char=25|end_char=32", "ner": "O"}, {"id": 7, "text": "en", "lemma": "en", "upos": "ADP", "head": 9, "deprel": "case", "misc": "start_char=33|end_char=35", "ner": "O"}, {"id": 8, "text": "30", "lemma": "30", "upos": "NUM", "head": 9, "deprel": "nummod", "misc": "start_char=36|end_char=38", "ner": "O"}, {"id": 9, "text": "minutes", "lemma": "minute", "upos": "NOUN", "feats": "Gender=Fem|Number=Plur", "head": 3, "deprel": "nmod", "misc": "start_char=39|end_char=46", "ner": "O"}, {"id": 10, "text": "abhisit", "lemma": "abhisit", "upos": "ADJ", "feats": "Gender=Fem|Number=Plur", "head": 9, "deprel": "amod", "misc": "start_char=47|end_char=54", "ner": "O"}, {"id": 11, "text": ".", "lemma": ".", "upos": "PUNCT", "head": 1, "deprel": "punct", "misc": "start_char=54|end_char=55", "ner": "O"}], [{"id": 1, "text": "Fils", "lemma": "fils", "upos": "NOUN", "feats": "Gender=Masc|Number=Sing", "head": 0, "deprel": "root", "misc": "start_char=56|end_char=60", "ner": "O"}, {"id": 2, "text": "de", "lemma": "de", "upos": "ADP", "head": 4, "deprel": "case", "misc": "start_char=61|end_char=63", "ner": "O"}, {"id": 3, "text": "l'", "lemma": "le", "upos": "DET", "feats": "Definite=Def|Gender=Masc|Number=Sing|PronType=Art", "head": 4, "deprel": "det", "misc": "start_char=64|end_char=66", "ner": "O"}, {"id": 4, "text": "acteur", "lemma": "acteur", "upos": "NOUN", "feats": "Gender=Masc|Number=Sing", "head": 1, "deprel": "nmod", "misc": "start_char=66|end_char=72", "ner": "O"}, {"id": 5, "text": ".", "lemma": ".", "upos": "PUNCT", "head": 1, "deprel": "punct", "misc": "start_char=72|end_char=73", "ner": "O"}], [{"id": 1, "text": "C'", "lemma": "ce", "upos": "PRON", "feats": "Number=Sing|Person=3|PronType=Dem", "head": 5, "deprel": "nsubj", "misc": "start_char=74|end_char=76", "ner": "O"}, {"id": 2, "text": "est", "lemma": "\u00eatre", "upos": "AUX", "feats": "Mood=Ind|Number=Sing|Person=3|Tense=Pres|VerbForm=Fin", "head": 5, "deprel": "cop", "misc": "start_char=76|end_char=79", "ner": "O"}, {"id": 3, "text": "mon", "lemma": "son", "upos": "DET", "feats": "Gender=Masc|Number=Sing|Poss=Yes|PronType=Prs", "head": 5, "deprel": "det", "misc": "start_char=80|end_char=83", "ner": "O"}, {"id": 4, "text": "petit", "lemma": "petit", "upos": "ADJ", "feats": "Gender=Masc|Number=Sing", "head": 5, "deprel": "amod", "misc": "start_char=84|end_char=89", "ner": "O"}, {"id": 5, "text": "ct", "lemma": "ct", "upos": "NOUN", "feats": "Gender=Masc|Number=Sing", "head": 0, "deprel": "root", "misc": "start_char=90|end_char=92", "ner": "O"}, {"id": 6, "text": "les", "lemma": "le", "upos": "DET", "feats": "Definite=Def|Gender=Masc|Number=Plur|PronType=Art", "head": 7, "deprel": "det", "misc": "start_char=93|end_char=96", "ner": "O"}, {"id": 7, "text": "bling", "lemma": "bling", "upos": "NOUN", "feats": "Gender=Masc|Number=Sing", "head": 5, "deprel": "appos", "misc": "start_char=97|end_char=102", "ner": "O"}, {"id": 8, "text": ".", "lemma": ".", "upos": "PUNCT", "head": 5, "deprel": "punct", "misc": "start_char=102|end_char=103", "ner": "O"}], [{"id": 1, "text": "Il", "lemma": "il", "upos": "PRON", "feats": "Gender=Masc|Number=Sing|Person=3|PronType=Prs", "head": 2, "deprel": "nsubj", "misc": "start_char=104|end_char=106", "ner": "O"}, {"id": 2, "text": "ya", "lemma": "aller", "upos": "VERB", "feats": "Mood=Ind|Number=Sing|Person=3|Tense=Pres|VerbForm=Fin", "head": 0, "deprel": "root", "misc": "start_char=107|end_char=109", "ner": "O"}, {"id": 3, "text": "des", "lemma": "un", "upos": "DET", "feats": "Definite=Ind|Gender=Masc|Number=Plur|PronType=Art", "head": 4, "deprel": "det", "misc": "start_char=110|end_char=113", "ner": "O"}, {"id": 4, "text": "choix", "lemma": "choix", "upos": "NOUN", "feats": "Gender=Masc|Number=Plur", "head": 2, "deprel": "obj", "misc": "start_char=114|end_char=119", "ner": "O"}, {"id": 5, "text": "affaire", "lemma": "affaire", "upos": "NOUN", "feats": "Gender=Fem|Number=Sing", "head": 4, "deprel": "nmod", "misc": "start_char=120|end_char=127", "ner": "O"}, {"id": 6, "text": "des", "lemma": "un", "upos": "DET", "feats": "Definite=Ind|Gender=Masc|Number=Plur|PronType=Art", "head": 7, "deprel": "det", "misc": "start_char=128|end_char=131", "ner": "O"}, {"id": 7, "text": "choix", "lemma": "choix", "upos": "NOUN", "feats": "Gender=Masc|Number=Plur", "head": 2, "deprel": "obj", "misc": "start_char=132|end_char=137", "ner": "O"}, {"id": 8, "text": "de", "lemma": "de", "upos": "ADP", "head": 9, "deprel": "case", "misc": "start_char=138|end_char=140", "ner": "O"}, {"id": 9, "text": "m", "lemma": "m", "upos": "NOUN", "feats": "Gender=Masc|Number=Plur", "head": 7, "deprel": "nmod", "misc": "start_char=141|end_char=142", "ner": "O"}, {"id": 10, "text": ".", "lemma": ".", "upos": "PUNCT", "head": 2, "deprel": "punct", "misc": "start_char=142|end_char=143", "ner": "O"}], [{"id": 1, "text": "Diffrentes", "lemma": "diffrent", "upos": "DET", "feats": "Gender=Fem|Number=Plur", "head": 2, "deprel": "det", "misc": "start_char=144|end_char=154", "ner": "S-MISC"}, {"id": 2, "text": "importances", "lemma": "importance", "upos": "NOUN", "feats": "Gender=Fem|Number=Plur", "head": 0, "deprel": "root", "misc": "start_char=155|end_char=166", "ner": "O"}, {"id": 3, "text": "et", "lemma": "et", "upos": "CCONJ", "head": 8, "deprel": "cc", "misc": "start_char=167|end_char=169", "ner": "O"}, {"id": 4, "text": "je", "lemma": "il", "upos": "PRON", "feats": "Number=Sing|Person=1|PronType=Prs", "head": 8, "deprel": "nsubj", "misc": "start_char=170|end_char=172", "ner": "O"}, {"id": 5, "text": "n'", "lemma": "ne", "upos": "ADV", "feats": "Polarity=Neg", "head": 8, "deprel": "advmod", "misc": "start_char=173|end_char=175", "ner": "O"}, {"id": 6, "text": "ai", "lemma": "avoir", "upos": "AUX", "feats": "Mood=Ind|Number=Sing|Person=1|Tense=Pres|VerbForm=Fin", "head": 8, "deprel": "aux:tense", "misc": "start_char=175|end_char=177", "ner": "O"}, {"id": 7, "text": "jamais", "lemma": "jamais", "upos": "ADV", "feats": "Polarity=Neg", "head": 8, "deprel": "advmod", "misc": "start_char=178|end_char=184", "ner": "O"}, {"id": 8, "text": "compris", "lemma": "comprendre", "upos": "VERB", "feats": "Gender=Masc|Number=Sing|Tense=Past|VerbForm=Part", "head": 2, "deprel": "conj", "misc": "start_char=185|end_char=192", "ner": "O"}, {"id": 9, "text": ".", "lemma": ".", "upos": "PUNCT", "head": 2, "deprel": "punct", "misc": "start_char=192|end_char=193", "ner": "O"}], [{"id": 1, "text": "Le", "lemma": "le", "upos": "DET", "feats": "Definite=Def|Gender=Masc|Number=Sing|PronType=Art", "head": 2, "deprel": "det", "misc": "start_char=194|end_char=196", "ner": "O"}, {"id": 2, "text": "choix", "lemma": "choix", "upos": "NOUN", "feats": "Gender=Masc|Number=Sing", "head": 0, "deprel": "root", "misc": "start_char=197|end_char=202", "ner": "O"}, {"id": 3, "text": "le", "lemma": "le", "upos": "DET", "feats": "Definite=Def|Gender=Masc|Number=Sing|PronType=Art", "head": 5, "deprel": "advmod", "misc": "start_char=203|end_char=205", "ner": "O"}, {"id": 4, "text": "plus", "lemma": "plus", "upos": "ADV", "head": 3, "deprel": "fixed", "misc": "start_char=206|end_char=210", "ner": "O"}, {"id": 5, "text": "dterminant", "lemma": "dterminant", "upos": "ADJ", "feats": "Gender=Masc|Number=Sing", "head": 2, "deprel": "amod", "misc": "start_char=211|end_char=221", "ner": "O"}, {"id": 6, "text": ".", "lemma": ".", "upos": "PUNCT", "head": 2, "deprel": "punct", "misc": "start_char=221|end_char=222", "ner": "O"}], [{"id": 1, "text": "Pavlik", "lemma": "Pavlik", "upos": "PROPN", "head": 0, "deprel": "root", "misc": "start_char=223|end_char=229", "ner": "S-PER"}, {"id": 2, "text": "gamin", "lemma": "gamin", "upos": "NOUN", "feats": "Gender=Masc|Number=Sing", "head": 1, "deprel": "appos", "misc": "start_char=230|end_char=235", "ner": "O"}, {"id": 3, "text": ".", "lemma": ".", "upos": "PUNCT", "head": 1, "deprel": "punct", "misc": "start_char=235|end_char=236", "ner": "O"}], [{"id": 1, "text": "Il", "lemma": "il", "upos": "PRON", "feats": "Gender=Masc|Number=Sing|Person=3|PronType=Prs", "head": 2, "deprel": "expl:subj", "misc": "start_char=237|end_char=239", "ner": "O"}, {"id": 2, "text": "faut", "lemma": "falloir", "upos": "VERB", "feats": "Mood=Ind|Number=Sing|Person=3|Tense=Pres|VerbForm=Fin", "head": 0, "deprel": "root", "misc": "start_char=240|end_char=244", "ner": "O"}, {"id": 3, "text": "le", "lemma": "le", "upos": "PRON", "feats": "Gender=Masc|Number=Sing|Person=3|PronType=Prs", "head": 4, "deprel": "obj", "misc": "start_char=245|end_char=247", "ner": "O"}, {"id": 4, "text": "prendre", "lemma": "prendre", "upos": "VERB", "feats": "VerbForm=Inf", "head": 2, "deprel": "ccomp", "misc": "start_char=248|end_char=255", "ner": "O"}, {"id": 5, "text": "dans", "lemma": "dans", "upos": "ADP", "head": 7, "deprel": "case", "misc": "start_char=256|end_char=260", "ner": "O"}, {"id": 6, "text": "ces", "lemma": "ce", "upos": "DET", "feats": "Gender=Masc|Number=Plur|PronType=Dem", "head": 7, "deprel": "det", "misc": "start_char=261|end_char=264", "ner": "O"}, {"id": 7, "text": "cas-l", "lemma": "cas-l", "upos": "NOUN", "feats": "Gender=Masc|Number=Plur", "head": 4, "deprel": "obl:mod", "misc": "start_char=265|end_char=270", "ner": "O"}, {"id": 8, "text": ".", "lemma": ".", "upos": "PUNCT", "head": 2, "deprel": "punct", "misc": "start_char=270|end_char=271", "ner": "O"}], [{"id": 1, "text": "Alors", "lemma": "alors", "upos": "ADV", "head": 4, "deprel": "mark", "misc": "start_char=272|end_char=277", "ner": "O"}, {"id": 2, "text": "qu'", "lemma": "que", "upos": "SCONJ", "head": 1, "deprel": "fixed", "misc": "start_char=278|end_char=281", "ner": "O"}, {"id": 3, "text": "europe", "lemma": "europe", "upos": "PROPN", "head": 4, "deprel": "nsubj", "misc": "start_char=281|end_char=287", "ner": "O"}, {"id": 4, "text": "cologie", "lemma": "cologier", "upos": "VERB", "feats": "Mood=Ind|Number=Sing|Person=3|Tense=Pres|VerbForm=Fin", "head": 11, "deprel": "advcl", "misc": "start_char=288|end_char=295", "ner": "O"}, {"id": 5, "text": "tmoins", "lemma": "tmoin", "upos": "ADJ", "feats": "Gender=Masc|Number=Sing", "head": 4, "deprel": "xcomp", "misc": "start_char=296|end_char=302", "ner": "O"}, {"id": 6, "text": "mais", "lemma": "mais", "upos": "CCONJ", "head": 11, "deprel": "cc", "misc": "start_char=303|end_char=307", "ner": "O"}, {"id": [7, 8], "text": "au", "ner": "O", "misc": "start_char=308|end_char=310"}, {"id": 7, "text": "\u00e0", "lemma": "\u00e0", "upos": "ADP", "head": 9, "deprel": "case"}, {"id": 8, "text": "le", "lemma": "le", "upos": "DET", "feats": "Definite=Def|Gender=Masc|Number=Sing|PronType=Art", "head": 9, "deprel": "det"}, {"id": 9, "text": "dbut", "lemma": "dbut", "upos": "NOUN", "feats": "Gender=Masc|Number=Sing", "head": 11, "deprel": "obl:mod", "misc": "start_char=311|end_char=315", "ner": "O"}, {"id": 10, "text": "je", "lemma": "il", "upos": "PRON", "feats": "Number=Sing|Person=1|PronType=Prs", "head": 11, "deprel": "nsubj", "misc": "start_char=316|end_char=318", "ner": "O"}, {"id": 11, "text": "voulais", "lemma": "vouloir", "upos": "VERB", "feats": "Mood=Ind|Number=Sing|Person=1|Tense=Imp|VerbForm=Fin", "head": 0, "deprel": "root", "misc": "start_char=319|end_char=326", "ner": "O"}, {"id": 12, "text": "avoir", "lemma": "avoir", "upos": "VERB", "feats": "VerbForm=Inf", "head": 11, "deprel": "xcomp", "misc": "start_char=327|end_char=332", "ner": "O"}, {"id": 13, "text": "un", "lemma": "un", "upos": "DET", "feats": "Definite=Ind|Gender=Masc|Number=Sing|PronType=Art", "head": 14, "deprel": "det", "misc": "start_char=333|end_char=335", "ner": "O"}, {"id": 14, "text": "impact", "lemma": "impact", "upos": "NOUN", "feats": "Gender=Masc|Number=Sing", "head": 12, "deprel": "obj", "misc": "start_char=336|end_char=342", "ner": "O"}, {"id": 15, "text": "sur", "lemma": "sur", "upos": "ADP", "head": 12, "deprel": "iobj", "misc": "start_char=343|end_char=346", "ner": "O"}, {"id": 16, "text": ".", "lemma": ".", "upos": "PUNCT", "head": 11, "deprel": "punct", "misc": "start_char=346|end_char=347", "ner": "O"}], [{"id": 1, "text": "Le", "lemma": "le", "upos": "DET", "feats": "Definite=Def|Gender=Masc|Number=Sing|PronType=Art", "head": 2, "deprel": "det", "misc": "start_char=348|end_char=350", "ner": "O"}, {"id": 2, "text": "reste", "lemma": "reste", "upos": "NOUN", "feats": "Gender=Masc|Number=Sing", "head": 0, "deprel": "root", "misc": "start_char=351|end_char=356", "ner": "O"}, {"id": 3, "text": "mais", "lemma": "mais", "upos": "CCONJ", "head": 5, "deprel": "cc", "misc": "start_char=357|end_char=361", "ner": "O"}, {"id": 4, "text": "je", "lemma": "il", "upos": "PRON", "feats": "Number=Sing|Person=1|PronType=Prs", "head": 5, "deprel": "nsubj", "misc": "start_char=362|end_char=364", "ner": "O"}, {"id": 5, "text": "crois", "lemma": "croire", "upos": "VERB", "feats": "Mood=Ind|Number=Sing|Person=1|Tense=Pres|VerbForm=Fin", "head": 2, "deprel": "conj", "misc": "start_char=365|end_char=370", "ner": "O"}, {"id": 6, "text": "que", "lemma": "que", "upos": "SCONJ", "head": 8, "deprel": "mark", "misc": "start_char=371|end_char=374", "ner": "O"}, {"id": 7, "text": "je", "lemma": "il", "upos": "PRON", "feats": "Number=Sing|Person=1|PronType=Prs", "head": 8, "deprel": "nsubj", "misc": "start_char=375|end_char=377", "ner": "O"}, {"id": 8, "text": "vais", "lemma": "aller", "upos": "VERB", "feats": "Mood=Ind|Number=Sing|Person=1|Tense=Pres|VerbForm=Fin", "head": 5, "deprel": "ccomp", "misc": "start_char=378|end_char=382", "ner": "O"}, {"id": 9, "text": "avoir", "lemma": "avoir", "upos": "VERB", "feats": "VerbForm=Inf", "head": 8, "deprel": "xcomp", "misc": "start_char=383|end_char=388", "ner": "O"}, {"id": 10, "text": "un", "lemma": "un", "upos": "DET", "feats": "Definite=Ind|Gender=Masc|Number=Sing|PronType=Art", "head": 11, "deprel": "det", "misc": "start_char=389|end_char=391", "ner": "O"}, {"id": 11, "text": "bac", "lemma": "bac", "upos": "NOUN", "feats": "Gender=Masc|Number=Sing", "head": 9, "deprel": "obj", "misc": "start_char=392|end_char=395", "ner": "O"}, {"id": 12, "text": "l", "lemma": "le", "upos": "DET", "feats": "Definite=Def|Gender=Masc|Number=Sing|PronType=Art", "head": 13, "deprel": "det", "misc": "start_char=396|end_char=397", "ner": "O"}, {"id": 13, "text": "enqute", "lemma": "enqute", "upos": "NOUN", "feats": "Gender=Masc|Number=Sing", "head": 9, "deprel": "obj", "misc": "start_char=398|end_char=404", "ner": "O"}, {"id": 14, "text": ".", "lemma": ".", "upos": "PUNCT", "head": 2, "deprel": "punct", "misc": "start_char=404|end_char=405", "ner": "O"}], [{"id": 1, "text": "Ce", "lemma": "ce", "upos": "DET", "feats": "Gender=Masc|Number=Sing|PronType=Dem", "head": 3, "deprel": "det", "misc": "start_char=406|end_char=408", "ner": "O"}, {"id": 2, "text": "jeune", "lemma": "jeune", "upos": "ADJ", "feats": "Gender=Masc|Number=Sing", "head": 3, "deprel": "amod", "misc": "start_char=409|end_char=414", "ner": "O"}, {"id": 3, "text": "franais", "lemma": "franais", "upos": "NOUN", "feats": "Gender=Masc|Number=Sing", "head": 0, "deprel": "root", "misc": "start_char=415|end_char=422", "ner": "O"}, {"id": 4, "text": ".", "lemma": ".", "upos": "PUNCT", "head": 3, "deprel": "punct", "misc": "start_char=422|end_char=423", "ner": "O"}], [{"id": 1, "text": "Tu", "lemma": "il", "upos": "PRON", "feats": "Number=Sing|Person=2|PronType=Prs", "head": 2, "deprel": "nsubj", "misc": "start_char=424|end_char=426", "ner": "O"}, {"id": 2, "text": "veux", "lemma": "vouloir", "upos": "VERB", "feats": "Mood=Ind|Number=Sing|Person=1|Tense=Pres|VerbForm=Fin", "head": 0, "deprel": "root", "misc": "start_char=427|end_char=431", "ner": "O"}, {"id": 3, "text": "faire", "lemma": "faire", "upos": "VERB", "feats": "VerbForm=Inf", "head": 2, "deprel": "xcomp", "misc": "start_char=432|end_char=437", "ner": "O"}, {"id": 4, "text": "un", "lemma": "un", "upos": "DET", "feats": "Definite=Ind|Gender=Masc|Number=Sing|PronType=Art", "head": 5, "deprel": "det", "misc": "start_char=438|end_char=440", "ner": "O"}, {"id": 5, "text": "papier", "lemma": "papier", "upos": "NOUN", "feats": "Gender=Masc|Number=Sing", "head": 3, "deprel": "obj", "misc": "start_char=441|end_char=447", "ner": "O"}, {"id": 6, "text": ".", "lemma": ".", "upos": "PUNCT", "head": 2, "deprel": "punct", "misc": "start_char=447|end_char=448", "ner": "O"}], [{"id": 1, "text": "Il", "lemma": "il", "upos": "PRON", "feats": "Gender=Masc|Number=Sing|Person=3|PronType=Prs", "head": 3, "deprel": "expl:subj", "misc": "start_char=449|end_char=451", "ner": "O"}, {"id": 2, "text": "y", "lemma": "y", "upos": "PRON", "head": 3, "deprel": "expl:comp", "misc": "start_char=452|end_char=453", "ner": "O"}, {"id": 3, "text": "avait", "lemma": "avoir", "upos": "VERB", "feats": "Mood=Ind|Number=Sing|Person=3|Tense=Imp|VerbForm=Fin", "head": 0, "deprel": "root", "misc": "start_char=454|end_char=459", "ner": "O"}, {"id": 4, "text": "un", "lemma": "un", "upos": "DET", "feats": "Definite=Ind|Gender=Masc|Number=Sing|PronType=Art", "head": 5, "deprel": "det", "misc": "start_char=460|end_char=462", "ner": "O"}, {"id": 5, "text": "problme", "lemma": "problme", "upos": "NOUN", "feats": "Gender=Masc|Number=Sing", "head": 3, "deprel": "obj", "misc": "start_char=463|end_char=470", "ner": "O"}, {"id": 6, "text": "srieux", "lemma": "srieux", "upos": "ADJ", "feats": "Gender=Masc|Number=Sing", "head": 5, "deprel": "amod", "misc": "start_char=471|end_char=477", "ner": "O"}, {"id": 7, "text": ".", "lemma": ".", "upos": "PUNCT", "head": 3, "deprel": "punct", "misc": "start_char=477|end_char=478", "ner": "O"}], [{"id": 1, "text": "Je", "lemma": "il", "upos": "PRON", "feats": "Number=Sing|Person=1|PronType=Prs", "head": 3, "deprel": "nsubj", "misc": "start_char=479|end_char=481", "ner": "O"}, {"id": 2, "text": "ne", "lemma": "ne", "upos": "ADV", "feats": "Polarity=Neg", "head": 3, "deprel": "advmod", "misc": "start_char=482|end_char=484", "ner": "O"}, {"id": 3, "text": "comprends", "lemma": "comprendre", "upos": "VERB", "feats": "Mood=Ind|Number=Sing|Person=1|Tense=Pres|VerbForm=Fin", "head": 0, "deprel": "root", "misc": "start_char=485|end_char=494", "ner": "O"}, {"id": 4, "text": "pas", "lemma": "pas", "upos": "ADV", "feats": "Polarity=Neg", "head": 3, "deprel": "advmod", "misc": "start_char=495|end_char=498", "ner": "O"}, {"id": 5, "text": "pourquoi", "lemma": "pourquoi", "upos": "ADV", "head": 8, "deprel": "advmod", "misc": "start_char=499|end_char=507", "ner": "O"}, {"id": 6, "text": "les", "lemma": "le", "upos": "DET", "feats": "Definite=Def|Gender=Masc|Number=Plur|PronType=Art", "head": 7, "deprel": "det", "misc": "start_char=508|end_char=511", "ner": "O"}, {"id": 7, "text": "bleus", "lemma": "bleu", "upos": "NOUN", "feats": "Gender=Masc|Number=Plur", "head": 8, "deprel": "nsubj", "misc": "start_char=512|end_char=517", "ner": "O"}, {"id": 8, "text": "l", "lemma": "le", "upos": "VERB", "feats": "Mood=Ind|Number=Plur|Person=3|Tense=Pres|VerbForm=Fin", "head": 3, "deprel": "ccomp", "misc": "start_char=518|end_char=519", "ner": "O"}, {"id": 9, "text": "donc", "lemma": "donc", "upos": "ADV", "head": 8, "deprel": "advmod", "misc": "start_char=520|end_char=524", "ner": "O"}, {"id": 10, "text": "pour", "lemma": "pour", "upos": "ADP", "head": 12, "deprel": "case", "misc": "start_char=525|end_char=529", "ner": "O"}, {"id": 11, "text": "la", "lemma": "le", "upos": "DET", "feats": "Definite=Def|Gender=Fem|Number=Sing|PronType=Art", "head": 12, "deprel": "det", "misc": "start_char=530|end_char=532", "ner": "O"}, {"id": 12, "text": "temporada", "lemma": "temporada", "upos": "NOUN", "feats": "Gender=Fem|Number=Sing", "head": 8, "deprel": "obl", "misc": "start_char=533|end_char=542", "ner": "O"}, {"id": 13, "text": ".", "lemma": ".", "upos": "PUNCT", "head": 3, "deprel": "punct", "misc": "start_char=542|end_char=543", "ner": "O"}], [{"id": 1, "text": "Ds", "lemma": "de", "upos": "INTJ", "head": 4, "deprel": "discourse", "misc": "start_char=544|end_char=546", "ner": "S-MISC"}, {"id": 2, "text": "la", "lemma": "le", "upos": "DET", "feats": "Definite=Def|Gender=Fem|Number=Sing|PronType=Art", "head": 4, "deprel": "det", "misc": "start_char=547|end_char=549", "ner": "O"}, {"id": 3, "text": "15", "lemma": "15", "upos": "NUM", "head": 4, "deprel": "nummod", "misc": "start_char=550|end_char=552", "ner": "O"}, {"id": 4, "text": "ans", "lemma": "an", "upos": "NOUN", "feats": "Gender=Masc|Number=Plur", "head": 0, "deprel": "root", "misc": "start_char=553|end_char=556", "ner": "O"}, {"id": 5, "text": "qui", "lemma": "qui", "upos": "PRON", "feats": "PronType=Rel", "head": 8, "deprel": "nsubj", "misc": "start_char=557|end_char=560", "ner": "O"}, {"id": 6, "text": "s'", "lemma": "se", "upos": "PRON", "feats": "Person=3|PronType=Prs", "head": 8, "deprel": "expl:comp", "misc": "start_char=561|end_char=563", "ner": "O"}, {"id": 7, "text": "est", "lemma": "\u00eatre", "upos": "AUX", "feats": "Mood=Ind|Number=Sing|Person=3|Tense=Pres|VerbForm=Fin", "head": 8, "deprel": "aux:tense", "misc": "start_char=563|end_char=566", "ner": "O"}, {"id": 8, "text": "pass", "lemma": "passer", "upos": "VERB", "feats": "Gender=Masc|Number=Sing|Tense=Past|VerbForm=Part", "head": 4, "deprel": "acl:relcl", "misc": "start_char=567|end_char=571", "ner": "O"}, {"id": 9, "text": ".", "lemma": ".", "upos": "PUNCT", "head": 4, "deprel": "punct", "misc": "start_char=571|end_char=572", "ner": "O"}], [{"id": 1, "text": "Elle", "lemma": "il", "upos": "PRON", "feats": "Gender=Fem|Number=Sing|Person=3|PronType=Prs", "head": 2, "deprel": "nsubj", "misc": "start_char=573|end_char=577", "ner": "O"}, {"id": 2, "text": "permet", "lemma": "permettre", "upos": "VERB", "feats": "Mood=Ind|Number=Sing|Person=3|Tense=Pres|VerbForm=Fin", "head": 0, "deprel": "root", "misc": "start_char=578|end_char=584", "ner": "O"}, {"id": 3, "text": "des", "lemma": "un", "upos": "DET", "feats": "Definite=Ind|Gender=Masc|Number=Plur|PronType=Art", "head": 4, "deprel": "det", "misc": "start_char=586|end_char=589", "ner": "O"}, {"id": 4, "text": "gens", "lemma": "gens", "upos": "NOUN", "feats": "Gender=Masc|Number=Plur", "head": 2, "deprel": "obj", "misc": "start_char=590|end_char=594", "ner": "O"}, {"id": 5, "text": "qui", "lemma": "qui", "upos": "PRON", "feats": "PronType=Rel", "head": 6, "deprel": "nsubj", "misc": "start_char=595|end_char=598", "ner": "O"}, {"id": 6, "text": "pensent", "lemma": "penser", "upos": "VERB", "feats": "Mood=Ind|Number=Plur|Person=3|Tense=Pres|VerbForm=Fin", "head": 4, "deprel": "acl:relcl", "misc": "start_char=599|end_char=606", "ner": "O"}, {"id": 7, "text": "qu'", "lemma": "que", "upos": "SCONJ", "head": 10, "deprel": "case", "misc": "start_char=607|end_char=610", "ner": "O"}, {"id": 8, "text": "eux", "lemma": "soi", "upos": "PRON", "feats": "Gender=Masc|Number=Plur|Person=3", "head": 6, "deprel": "obl", "misc": "start_char=611|end_char=614", "ner": "O"}, {"id": 9, "text": "mmes", "lemma": "son", "upos": "DET", "feats": "Definite=Def|Gender=Masc|Number=Plur|PronType=Art", "head": 10, "deprel": "det", "misc": "start_char=615|end_char=619", "ner": "O"}, {"id": 10, "text": "joueurs", "lemma": "joueur", "upos": "NOUN", "feats": "Gender=Masc|Number=Plur", "head": 6, "deprel": "obj", "misc": "start_char=620|end_char=627", "ner": "O"}, {"id": 11, "text": "pokernews", "lemma": "pokernew", "upos": "ADJ", "feats": "Gender=Masc|Number=Plur", "head": 10, "deprel": "amod", "misc": "start_char=628|end_char=637", "ner": "O"}, {"id": 12, "text": ".", "lemma": ".", "upos": "PUNCT", "head": 2, "deprel": "punct", "misc": "start_char=637|end_char=638", "ner": "O"}], [{"id": 1, "text": "Mais", "lemma": "mais", "upos": "CCONJ", "head": 4, "deprel": "cc", "misc": "start_char=639|end_char=643", "ner": "O"}, {"id": 2, "text": "les", "lemma": "le", "upos": "DET", "feats": "Definite=Def|Gender=Fem|Number=Plur|PronType=Art", "head": 3, "deprel": "det", "misc": "start_char=644|end_char=647", "ner": "O"}, {"id": 3, "text": "voitures", "lemma": "voiture", "upos": "NOUN", "feats": "Gender=Fem|Number=Plur", "head": 4, "deprel": "nsubj", "misc": "start_char=648|end_char=656", "ner": "O"}, {"id": 4, "text": "permettent", "lemma": "permettre", "upos": "VERB", "feats": "Mood=Ind|Number=Plur|Person=3|Tense=Pres|VerbForm=Fin", "head": 0, "deprel": "root", "misc": "start_char=657|end_char=667", "ner": "O"}, {"id": 5, "text": "des", "lemma": "un", "upos": "DET", "feats": "Definite=Ind|Gender=Masc|Number=Plur|PronType=Art", "head": 6, "deprel": "det", "misc": "start_char=669|end_char=672", "ner": "O"}, {"id": 6, "text": "choix", "lemma": "choix", "upos": "NOUN", "feats": "Gender=Masc|Number=Plur", "head": 4, "deprel": "obj", "misc": "start_char=673|end_char=678", "ner": "O"}, {"id": 7, "text": ".", "lemma": ".", "upos": "PUNCT", "head": 4, "deprel": "punct", "misc": "start_char=678|end_char=679", "ner": "O"}], [{"id": 1, "text": "Aucune", "lemma": "aucun", "upos": "DET", "feats": "Gender=Fem|Number=Sing|Polarity=Neg|PronType=Neg", "head": 2, "deprel": "det", "misc": "start_char=680|end_char=686", "ner": "S-LOC"}, {"id": 2, "text": "importance", "lemma": "importance", "upos": "NOUN", "feats": "Gender=Fem|Number=Sing", "head": 11, "deprel": "nsubj", "misc": "start_char=687|end_char=697", "ner": "O"}, {"id": 3, "text": "d'", "lemma": "de", "upos": "ADP", "head": 4, "deprel": "case", "misc": "start_char=698|end_char=700", "ner": "O"}, {"id": 4, "text": "lite", "lemma": "lite", "upos": "NOUN", "feats": "Gender=Masc|Number=Sing", "head": 2, "deprel": "nmod", "misc": "start_char=700|end_char=704", "ner": "O"}, {"id": 5, "text": "les", "lemma": "le", "upos": "DET", "feats": "Definite=Def|Gender=Masc|Number=Plur|PronType=Art", "head": 6, "deprel": "det", "misc": "start_char=705|end_char=708", "ner": "O"}, {"id": 6, "text": "choix", "lemma": "choix", "upos": "NOUN", "feats": "Gender=Masc|Number=Plur", "head": 2, "deprel": "appos", "misc": "start_char=709|end_char=714", "ner": "O"}, {"id": [7, 8], "text": "du", "ner": "O", "misc": "start_char=715|end_char=717"}, {"id": 7, "text": "de", "lemma": "de", "upos": "ADP", "head": 9, "deprel": "case"}, {"id": 8, "text": "le", "lemma": "le", "upos": "DET", "feats": "Definite=Def|Gender=Masc|Number=Sing|PronType=Art", "head": 9, "deprel": "det"}, {"id": 9, "text": "bois", "lemma": "bois", "upos": "NOUN", "feats": "Gender=Masc|Number=Sing", "head": 6, "deprel": "nmod", "misc": "start_char=718|end_char=722", "ner": "O"}, {"id": 10, "text": "l'", "lemma": "le", "upos": "DET", "feats": "Definite=Def|Gender=Fem|Number=Sing|PronType=Art", "head": 11, "deprel": "det", "misc": "start_char=723|end_char=725", "ner": "O"}, {"id": 11, "text": "quipe", "lemma": "quiper", "upos": "VERB", "feats": "Mood=Ind|Number=Sing|Person=3|Tense=Pres|VerbForm=Fin", "head": 0, "deprel": "root", "misc": "start_char=725|end_char=730", "ner": "O"}, {"id": 12, "text": "d'", "lemma": "de", "upos": "ADP", "head": 13, "deprel": "case", "misc": "start_char=731|end_char=733", "ner": "O"}, {"id": 13, "text": "everton", "lemma": "everton", "upos": "NOUN", "feats": "Gender=Masc|Number=Sing", "head": 11, "deprel": "obl:arg", "misc": "start_char=733|end_char=740", "ner": "O"}, {"id": 14, "text": "content", "lemma": "content", "upos": "ADJ", "feats": "Gender=Masc|Number=Sing", "head": 13, "deprel": "amod", "misc": "start_char=741|end_char=748", "ner": "O"}, {"id": 15, "text": "pour", "lemma": "pour", "upos": "ADP", "head": 11, "deprel": "advmod", "misc": "start_char=749|end_char=753", "ner": "O"}, {"id": 16, "text": ".", "lemma": ".", "upos": "PUNCT", "head": 11, "deprel": "punct", "misc": "start_char=753|end_char=754", "ner": "O"}], [{"id": 1, "text": "Pour", "lemma": "pour", "upos": "ADP", "head": 0, "deprel": "root", "misc": "start_char=755|end_char=759", "ner": "O"}, {"id": 2, "text": "plus", "lemma": "plus", "upos": "ADV", "head": 1, "deprel": "fixed", "misc": "start_char=760|end_char=764", "ner": "O"}, {"id": 3, "text": "que", "lemma": "que", "upos": "SCONJ", "head": 5, "deprel": "case", "misc": "start_char=765|end_char=768", "ner": "O"}, {"id": 4, "text": "les", "lemma": "le", "upos": "DET", "feats": "Definite=Def|Gender=Masc|Number=Plur|PronType=Art", "head": 5, "deprel": "det", "misc": "start_char=769|end_char=772", "ner": "O"}, {"id": 5, "text": "choix", "lemma": "choix", "upos": "NOUN", "feats": "Gender=Masc|Number=Plur", "head": 1, "deprel": "obl:arg", "misc": "start_char=773|end_char=778", "ner": "O"}, {"id": 6, "text": "les", "lemma": "le", "upos": "DET", "feats": "Definite=Def|Number=Plur|PronType=Art", "head": 8, "deprel": "advmod", "misc": "start_char=779|end_char=782", "ner": "O"}, {"id": 7, "text": "plus", "lemma": "plus", "upos": "ADV", "head": 6, "deprel": "fixed", "misc": "start_char=783|end_char=787", "ner": "O"}, {"id": 8, "text": "importants", "lemma": "important", "upos": "ADJ", "feats": "Gender=Masc|Number=Plur", "head": 5, "deprel": "amod", "misc": "start_char=788|end_char=798", "ner": "O"}, {"id": 9, "text": "de", "lemma": "de", "upos": "ADP", "head": 10, "deprel": "case", "misc": "start_char=799|end_char=801", "ner": "O"}, {"id": 10, "text": "coupe", "lemma": "coupe", "upos": "NOUN", "feats": "Gender=Fem|Number=Sing", "head": 5, "deprel": "nmod", "misc": "start_char=802|end_char=807", "ner": "O"}, {"id": 11, "text": "davis", "lemma": "davis", "upos": "PROPN", "head": 10, "deprel": "appos", "misc": "start_char=808|end_char=813", "ner": "O"}, {"id": 12, "text": ".", "lemma": ".", "upos": "PUNCT", "head": 1, "deprel": "punct", "misc": "start_char=813|end_char=814", "ner": "O"}], [{"id": 1, "text": "Je", "lemma": "il", "upos": "PRON", "feats": "Number=Sing|Person=1|PronType=Prs", "head": 2, "deprel": "nsubj", "misc": "start_char=815|end_char=817", "ner": "O"}, {"id": 2, "text": "pense", "lemma": "penser", "upos": "VERB", "feats": "Mood=Ind|Number=Sing|Person=1|Tense=Pres|VerbForm=Fin", "head": 0, "deprel": "root", "misc": "start_char=818|end_char=823", "ner": "O"}, {"id": 3, "text": "notamment", "lemma": "notamment", "upos": "ADV", "head": 2, "deprel": "advmod", "misc": "start_char=824|end_char=833", "ner": "O"}, {"id": 4, "text": ".", "lemma": ".", "upos": "PUNCT", "head": 2, "deprel": "punct", "misc": "start_char=833|end_char=834", "ner": "O"}], [{"id": 1, "text": "L'", "lemma": "le", "upos": "DET", "feats": "Definite=Def|Gender=Masc|Number=Sing|PronType=Art", "head": 2, "deprel": "det", "misc": "start_char=835|end_char=837", "ner": "O"}, {"id": 2, "text": "ascenseur", "lemma": "ascenseur", "upos": "NOUN", "feats": "Gender=Masc|Number=Sing", "head": 0, "deprel": "root", "misc": "start_char=837|end_char=846", "ner": "O"}, {"id": 3, "text": "qui", "lemma": "qui", "upos": "PRON", "feats": "PronType=Rel", "head": 4, "deprel": "nsubj", "misc": "start_char=847|end_char=850", "ner": "O"}, {"id": 4, "text": "veut", "lemma": "vouloir", "upos": "VERB", "feats": "Mood=Ind|Number=Sing|Person=3|Tense=Pres|VerbForm=Fin", "head": 2, "deprel": "acl:relcl", "misc": "start_char=851|end_char=855", "ner": "O"}, {"id": 5, "text": "pas", "lemma": "pas", "upos": "ADV", "feats": "Polarity=Neg", "head": 4, "deprel": "advmod", "misc": "start_char=856|end_char=859", "ner": "O"}, {"id": 6, "text": "descendre", "lemma": "descendre", "upos": "VERB", "feats": "VerbForm=Inf", "head": 4, "deprel": "xcomp", "misc": "start_char=860|end_char=869", "ner": "O"}, {"id": 7, "text": ".", "lemma": ".", "upos": "PUNCT", "head": 2, "deprel": "punct", "misc": "start_char=869|end_char=870", "ner": "O"}], [{"id": 1, "text": "Il", "lemma": "il", "upos": "PRON", "feats": "Gender=Masc|Number=Sing|Person=3|PronType=Prs", "head": 4, "deprel": "nsubj", "misc": "start_char=871|end_char=873", "ner": "O"}, {"id": 2, "text": "est", "lemma": "\u00eatre", "upos": "AUX", "feats": "Mood=Ind|Number=Sing|Person=3|Tense=Pres|VerbForm=Fin", "head": 4, "deprel": "cop", "misc": "start_char=874|end_char=877", "ner": "O"}, {"id": 3, "text": "long", "lemma": "long", "upos": "ADJ", "feats": "Gender=Masc|Number=Sing", "head": 4, "deprel": "xcomp", "misc": "start_char=878|end_char=882", "ner": "O"}, {"id": 4, "text": "sont", "lemma": "\u00eatre", "upos": "VERB", "feats": "Mood=Ind|Number=Plur|Person=3|Tense=Pres|VerbForm=Fin", "head": 0, "deprel": "root", "misc": "start_char=883|end_char=887", "ner": "O"}, {"id": 5, "text": "pas", "lemma": "pas", "upos": "ADV", "feats": "Polarity=Neg", "head": 4, "deprel": "advmod", "misc": "start_char=888|end_char=891", "ner": "O"}, {"id": 6, "text": "sans", "lemma": "sans", "upos": "ADP", "head": 7, "deprel": "mark", "misc": "start_char=892|end_char=896", "ner": "O"}, {"id": 7, "text": "savoir", "lemma": "savoir", "upos": "VERB", "feats": "VerbForm=Inf", "head": 4, "deprel": "advcl", "misc": "start_char=897|end_char=903", "ner": "O"}, {"id": 8, "text": ".", "lemma": ".", "upos": "PUNCT", "head": 4, "deprel": "punct", "misc": "start_char=903|end_char=904", "ner": "O"}], [{"id": 1, "text": "Lors", "lemma": "lors", "upos": "ADV", "head": 8, "deprel": "advmod", "misc": "start_char=905|end_char=909", "ner": "O"}, {"id": [2, 3], "text": "du", "ner": "O", "misc": "start_char=910|end_char=912"}, {"id": 2, "text": "de", "lemma": "de", "upos": "ADP", "head": 5, "deprel": "case"}, {"id": 3, "text": "le", "lemma": "le", "upos": "DET", "feats": "Definite=Def|Gender=Masc|Number=Sing|PronType=Art", "head": 5, "deprel": "det"}, {"id": 4, "text": "premier", "lemma": "premier", "upos": "ADJ", "feats": "Gender=Masc|Number=Sing", "head": 5, "deprel": "amod", "misc": "start_char=913|end_char=920", "ner": "O"}, {"id": 5, "text": "skate", "lemma": "skate", "upos": "NOUN", "feats": "Gender=Masc|Number=Sing", "head": 1, "deprel": "obl:arg", "misc": "start_char=921|end_char=926", "ner": "O"}, {"id": 6, "text": "la", "lemma": "le", "upos": "DET", "feats": "Definite=Def|Gender=Fem|Number=Sing|PronType=Art", "head": 7, "deprel": "det", "misc": "start_char=927|end_char=929", "ner": "O"}, {"id": 7, "text": "chorale", "lemma": "chorale", "upos": "NOUN", "feats": "Gender=Fem|Number=Sing", "head": 8, "deprel": "nsubj", "misc": "start_char=930|end_char=937", "ner": "O"}, {"id": 8, "text": "dirige", "lemma": "diriger", "upos": "VERB", "feats": "Mood=Ind|Number=Sing|Person=3|Tense=Pres|VerbForm=Fin", "head": 0, "deprel": "root", "misc": "start_char=938|end_char=944", "ner": "O"}, {"id": 9, "text": "par", "lemma": "par", "upos": "ADP", "head": 11, "deprel": "case", "misc": "start_char=945|end_char=948", "ner": "O"}, {"id": 10, "text": "l'", "lemma": "le", "upos": "DET", "feats": "Definite=Def|Gender=Masc|Number=Sing|PronType=Art", "head": 11, "deprel": "det", "misc": "start_char=949|end_char=951", "ner": "O"}, {"id": 11, "text": "escalier", "lemma": "escalier", "upos": "NOUN", "feats": "Gender=Masc|Number=Sing", "head": 8, "deprel": "obl:arg", "misc": "start_char=951|end_char=959", "ner": "O"}, {"id": 12, "text": ".", "lemma": ".", "upos": "PUNCT", "head": 8, "deprel": "punct", "misc": "start_char=959|end_char=960", "ner": "O"}], [{"id": 1, "text": "Pourtant", "lemma": "pourtant", "upos": "ADV", "head": 5, "deprel": "advmod", "misc": "start_char=961|end_char=969", "ner": "O"}, {"id": 2, "text": "ces", "lemma": "ce", "upos": "DET", "feats": "Gender=Fem|Number=Plur|PronType=Dem", "head": 4, "deprel": "det", "misc": "start_char=970|end_char=973", "ner": "O"}, {"id": 3, "text": "cinq", "lemma": "cinq", "upos": "NUM", "head": 4, "deprel": "nummod", "misc": "start_char=974|end_char=978", "ner": "O"}, {"id": 4, "text": "minutes", "lemma": "minute", "upos": "NOUN", "feats": "Gender=Fem|Number=Plur", "head": 5, "deprel": "nmod", "misc": "start_char=979|end_char=986", "ner": "O"}, {"id": 5, "text": "dj", "lemma": "dj", "upos": "NOUN", "feats": "Gender=Masc|Number=Plur", "head": 0, "deprel": "root", "misc": "start_char=987|end_char=989", "ner": "O"}, {"id": 6, "text": "fortement", "lemma": "fortement", "upos": "ADV", "head": 7, "deprel": "advmod", "misc": "start_char=990|end_char=999", "ner": "O"}, {"id": 7, "text": "mobiliss", "lemma": "mobilis", "upos": "ADJ", "feats": "Gender=Masc|Number=Plur", "head": 5, "deprel": "amod", "misc": "start_char=1000|end_char=1008", "ner": "O"}, {"id": 8, "text": "en", "lemma": "en", "upos": "ADP", "head": 9, "deprel": "mark", "misc": "start_char=1009|end_char=1011", "ner": "O"}, {"id": 9, "text": "attendant", "lemma": "attendre", "upos": "VERB", "feats": "Tense=Pres|VerbForm=Part", "head": 5, "deprel": "acl", "misc": "start_char=1012|end_char=1021", "ner": "O"}, {"id": 10, "text": "les", "lemma": "le", "upos": "DET", "feats": "Definite=Def|Gender=Masc|Number=Plur|PronType=Art", "head": 12, "deprel": "det", "misc": "start_char=1022|end_char=1025", "ner": "O"}, {"id": 11, "text": ".", "lemma": ".", "upos": "PUNCT", "head": 12, "deprel": "punct", "misc": "start_char=1025|end_char=1026", "ner": "O"}, {"id": 12, "text": "Barbares", "lemma": "Barbare", "upos": "ADJ", "feats": "Gender=Masc|Number=Plur", "head": 9, "deprel": "obj", "misc": "start_char=1027|end_char=1035", "ner": "S-MISC"}, {"id": 13, "text": ".", "lemma": ".", "upos": "PUNCT", "head": 5, "deprel": "punct", "misc": "start_char=1035|end_char=1036", "ner": "O"}], [{"id": 1, "text": "C'", "lemma": "ce", "upos": "PRON", "feats": "Number=Sing|Person=3|PronType=Dem", "head": 2, "deprel": "expl:subj", "misc": "start_char=1037|end_char=1039", "ner": "O"}, {"id": 2, "text": "est", "lemma": "\u00eatre", "upos": "VERB", "feats": "Mood=Ind|Number=Sing|Person=3|Tense=Pres|VerbForm=Fin", "head": 0, "deprel": "root", "misc": "start_char=1039|end_char=1042", "ner": "O"}, {"id": 3, "text": "comprendre", "lemma": "comprendre", "upos": "VERB", "feats": "VerbForm=Inf", "head": 2, "deprel": "ccomp", "misc": "start_char=1043|end_char=1053", "ner": "O"}, {"id": 4, "text": "ce", "lemma": "ce", "upos": "PRON", "feats": "Number=Sing|Person=3|PronType=Dem", "head": 3, "deprel": "obj", "misc": "start_char=1054|end_char=1056", "ner": "O"}, {"id": 5, "text": "qu'", "lemma": "que", "upos": "PRON", "feats": "PronType=Rel", "head": 8, "deprel": "obj", "misc": "start_char=1057|end_char=1060", "ner": "O"}, {"id": 6, "text": "elles", "lemma": "il", "upos": "PRON", "feats": "Gender=Fem|Number=Plur|Person=3|PronType=Prs", "head": 7, "deprel": "nsubj", "misc": "start_char=1060|end_char=1065", "ner": "O"}, {"id": 7, "text": "vont", "lemma": "aller", "upos": "VERB", "feats": "Mood=Ind|Number=Plur|Person=3|Tense=Pres|VerbForm=Fin", "head": 4, "deprel": "acl:relcl", "misc": "start_char=1066|end_char=1070", "ner": "O"}, {"id": 8, "text": "faire", "lemma": "faire", "upos": "VERB", "feats": "VerbForm=Inf", "head": 7, "deprel": "xcomp", "misc": "start_char=1071|end_char=1076", "ner": "O"}, {"id": 9, "text": "pour", "lemma": "pour", "upos": "ADP", "head": 10, "deprel": "case", "misc": "start_char=1077|end_char=1081", "ner": "O"}, {"id": 10, "text": "nous", "lemma": "il", "upos": "PRON", "feats": "Number=Plur|Person=1|PronType=Prs", "head": 13, "deprel": "obl:mod", "misc": "start_char=1082|end_char=1086", "ner": "O"}, {"id": 11, "text": "c'", "lemma": "ce", "upos": "PRON", "feats": "Number=Sing|Person=3|PronType=Dem", "head": 13, "deprel": "nsubj", "misc": "start_char=1087|end_char=1089", "ner": "O"}, {"id": 12, "text": "est", "lemma": "\u00eatre", "upos": "AUX", "feats": "Mood=Ind|Number=Sing|Person=3|Tense=Pres|VerbForm=Fin", "head": 17, "deprel": "cop", "misc": "start_char=1089|end_char=1092", "ner": "O"}, {"id": 13, "text": "quoi", "lemma": "quoi", "upos": "PRON", "head": 17, "deprel": "nsubj", "misc": "start_char=1093|end_char=1097", "ner": "O"}, {"id": 14, "text": "un", "lemma": "un", "upos": "DET", "feats": "Definite=Ind|Gender=Masc|Number=Sing|PronType=Art", "head": 16, "deprel": "advmod", "misc": "start_char=1098|end_char=1100", "ner": "O"}, {"id": 15, "text": "peu", "lemma": "peu", "upos": "ADV", "head": 14, "deprel": "fixed", "misc": "start_char=1101|end_char=1104", "ner": "O"}, {"id": 16, "text": "plus", "lemma": "plus", "upos": "ADV", "head": 17, "deprel": "advmod", "misc": "start_char=1105|end_char=1109", "ner": "O"}, {"id": 17, "text": "loin", "lemma": "loin", "upos": "ADV", "head": 8, "deprel": "advmod", "misc": "start_char=1110|end_char=1114", "ner": "O"}, {"id": 18, "text": ".", "lemma": ".", "upos": "PUNCT", "head": 2, "deprel": "punct", "misc": "start_char=1114|end_char=1115", "ner": "O"}], [{"id": 1, "text": "Malherbe", "lemma": "Malherbe", "upos": "PROPN", "head": 0, "deprel": "root", "misc": "start_char=1116|end_char=1124", "ner": "S-PER"}, {"id": 2, "text": ".", "lemma": ".", "upos": "PUNCT", "head": 1, "deprel": "punct", "misc": "start_char=1124|end_char=1125", "ner": "O"}], [{"id": 1, "text": "Pour", "lemma": "pour", "upos": "ADP", "head": 3, "deprel": "mark", "misc": "start_char=1126|end_char=1130", "ner": "O"}, {"id": 2, "text": "l'", "lemma": "le", "upos": "PRON", "feats": "Number=Sing|Person=3|PronType=Prs", "head": 3, "deprel": "obj", "misc": "start_char=1131|end_char=1133", "ner": "O"}, {"id": 3, "text": "installer", "lemma": "installer", "upos": "VERB", "feats": "VerbForm=Inf", "head": 0, "deprel": "root", "misc": "start_char=1133|end_char=1142", "ner": "O"}, {"id": 4, "text": ".", "lemma": ".", "upos": "PUNCT", "head": 3, "deprel": "punct", "misc": "start_char=1142|end_char=1143", "ner": "O"}], [{"id": 1, "text": "En", "lemma": "en", "upos": "ADP", "head": 5, "deprel": "advmod", "misc": "start_char=1144|end_char=1146", "ner": "O"}, {"id": 2, "text": "fait", "lemma": "fait", "upos": "NOUN", "feats": "Gender=Masc|Number=Sing", "head": 1, "deprel": "fixed", "misc": "start_char=1147|end_char=1151", "ner": "O"}, {"id": 3, "text": "j'", "lemma": "il", "upos": "PRON", "feats": "Number=Sing|Person=1|PronType=Prs", "head": 5, "deprel": "nsubj", "misc": "start_char=1152|end_char=1154", "ner": "O"}, {"id": 4, "text": "y", "lemma": "y", "upos": "PRON", "head": 5, "deprel": "obl:mod", "misc": "start_char=1154|end_char=1155", "ner": "O"}, {"id": 5, "text": "rflchis", "lemma": "rflchir", "upos": "VERB", "feats": "Mood=Ind|Number=Sing|Person=1|Tense=Pres|VerbForm=Fin", "head": 0, "deprel": "root", "misc": "start_char=1156|end_char=1163", "ner": "O"}, {"id": 6, "text": ".", "lemma": ".", "upos": "PUNCT", "head": 5, "deprel": "punct", "misc": "start_char=1163|end_char=1164", "ner": "O"}], [{"id": 1, "text": "La", "lemma": "le", "upos": "DET", "feats": "Definite=Def|Gender=Fem|Number=Sing|PronType=Art", "head": 2, "deprel": "det", "misc": "start_char=1165|end_char=1167", "ner": "O"}, {"id": 2, "text": "juge", "lemma": "juge", "upos": "NOUN", "feats": "Gender=Fem|Number=Sing", "head": 0, "deprel": "root", "misc": "start_char=1168|end_char=1172", "ner": "O"}, {"id": 3, "text": "de", "lemma": "de", "upos": "ADP", "head": 4, "deprel": "mark", "misc": "start_char=1173|end_char=1175", "ner": "O"}, {"id": 4, "text": "classer", "lemma": "classer", "upos": "VERB", "feats": "VerbForm=Inf", "head": 2, "deprel": "acl", "misc": "start_char=1176|end_char=1183", "ner": "O"}, {"id": 5, "text": ".", "lemma": ".", "upos": "PUNCT", "head": 2, "deprel": "punct", "misc": "start_char=1183|end_char=1184", "ner": "O"}], [{"id": 1, "text": "Les", "lemma": "le", "upos": "DET", "feats": "Definite=Def|Gender=Fem|Number=Plur|PronType=Art", "head": 2, "deprel": "det", "misc": "start_char=1185|end_char=1188", "ner": "S-LOC"}, {"id": 2, "text": "victoires", "lemma": "victoire", "upos": "NOUN", "feats": "Gender=Fem|Number=Plur", "head": 0, "deprel": "root", "misc": "start_char=1189|end_char=1198", "ner": "O"}, {"id": 3, "text": "en", "lemma": "en", "upos": "ADP", "head": 5, "deprel": "case", "misc": "start_char=1199|end_char=1201", "ner": "O"}, {"id": 4, "text": "deux", "lemma": "deux", "upos": "NUM", "head": 5, "deprel": "nummod", "misc": "start_char=1202|end_char=1206", "ner": "O"}, {"id": 5, "text": "catgories", "lemma": "catgorie", "upos": "NOUN", "feats": "Gender=Fem|Number=Plur", "head": 2, "deprel": "nmod", "misc": "start_char=1207|end_char=1216", "ner": "O"}, {"id": 6, "text": ".", "lemma": ".", "upos": "PUNCT", "head": 2, "deprel": "punct", "misc": "start_char=1216|end_char=1217", "ner": "O"}], [{"id": 1, "text": "Dans", "lemma": "dans", "upos": "ADP", "head": 3, "deprel": "case", "misc": "start_char=1218|end_char=1222", "ner": "O"}, {"id": 2, "text": "le", "lemma": "le", "upos": "DET", "feats": "Definite=Def|Gender=Masc|Number=Sing|PronType=Art", "head": 3, "deprel": "det", "misc": "start_char=1223|end_char=1225", "ner": "O"}, {"id": 3, "text": "choix", "lemma": "choix", "upos": "NOUN", "feats": "Gender=Masc|Number=Sing", "head": 0, "deprel": "root", "misc": "start_char=1226|end_char=1231", "ner": "O"}, {"id": 4, "text": "de", "lemma": "de", "upos": "ADP", "head": 6, "deprel": "case", "misc": "start_char=1232|end_char=1234", "ner": "O"}, {"id": 5, "text": "la", "lemma": "le", "upos": "DET", "feats": "Definite=Def|Gender=Fem|Number=Sing|PronType=Art", "head": 6, "deprel": "det", "misc": "start_char=1235|end_char=1237", "ner": "O"}, {"id": 6, "text": "scurit", "lemma": "scurit", "upos": "NOUN", "feats": "Gender=Fem|Number=Sing", "head": 3, "deprel": "nmod", "misc": "start_char=1238|end_char=1244", "ner": "O"}, {"id": 7, "text": ".", "lemma": ".", "upos": "PUNCT", "head": 3, "deprel": "punct", "misc": "start_char=1244|end_char=1245", "ner": "O"}], [{"id": 1, "text": "Une", "lemma": "un", "upos": "DET", "feats": "Definite=Ind|Gender=Fem|Number=Sing|PronType=Art", "head": 7, "deprel": "advmod", "misc": "start_char=1246|end_char=1249", "ner": "O"}, {"id": 2, "text": "fois", "lemma": "fois", "upos": "NOUN", "feats": "Gender=Fem|Number=Sing", "head": 1, "deprel": "fixed", "misc": "start_char=1250|end_char=1254", "ner": "O"}, {"id": 3, "text": "de", "lemma": "de", "upos": "ADP", "head": 1, "deprel": "fixed", "misc": "start_char=1255|end_char=1257", "ner": "O"}, {"id": 4, "text": "plus", "lemma": "plus", "upos": "ADV", "head": 3, "deprel": "fixed", "misc": "start_char=1258|end_char=1262", "ner": "O"}, {"id": 5, "text": "tout", "lemma": "tout", "upos": "ADJ", "feats": "Gender=Masc|Number=Sing", "head": 7, "deprel": "amod", "misc": "start_char=1263|end_char=1267", "ner": "O"}, {"id": 6, "text": "le", "lemma": "le", "upos": "DET", "feats": "Definite=Def|Gender=Masc|Number=Sing|PronType=Art", "head": 7, "deprel": "det", "misc": "start_char=1268|end_char=1270", "ner": "O"}, {"id": 7, "text": "temps", "lemma": "temps", "upos": "NOUN", "feats": "Gender=Masc|Number=Sing", "head": 0, "deprel": "root", "misc": "start_char=1271|end_char=1276", "ner": "O"}, {"id": 8, "text": ".", "lemma": ".", "upos": "PUNCT", "head": 7, "deprel": "punct", "misc": "start_char=1276|end_char=1277", "ner": "O"}], [{"id": 1, "text": "Nos", "lemma": "son", "upos": "DET", "feats": "Gender=Masc|Number=Plur|Poss=Yes|PronType=Prs", "head": 2, "deprel": "det", "misc": "start_char=1278|end_char=1281", "ner": "S-LOC"}, {"id": 2, "text": "problmes", "lemma": "problme", "upos": "NOUN", "feats": "Gender=Masc|Number=Plur", "head": 3, "deprel": "nsubj", "misc": "start_char=1282|end_char=1290", "ner": "O"}, {"id": 3, "text": "prcis", "lemma": "prcevoir", "upos": "VERB", "feats": "Mood=Ind|Number=Plur|Person=3|Tense=Pres|VerbForm=Fin", "head": 0, "deprel": "root", "misc": "start_char=1291|end_char=1296", "ner": "O"}, {"id": 4, "text": "vous", "lemma": "il", "upos": "PRON", "feats": "Number=Plur|Person=2|PronType=Prs", "head": 5, "deprel": "nsubj", "misc": "start_char=1297|end_char=1301", "ner": "O"}, {"id": 5, "text": "dire", "lemma": "dire", "upos": "VERB", "feats": "VerbForm=Inf", "head": 3, "deprel": "xcomp", "misc": "start_char=1302|end_char=1306", "ner": "O"}, {"id": 6, "text": "que", "lemma": "que", "upos": "SCONJ", "head": 9, "deprel": "mark", "misc": "start_char=1307|end_char=1310", "ner": "O"}, {"id": 7, "text": "je", "lemma": "il", "upos": "PRON", "feats": "Number=Sing|Person=1|PronType=Prs", "head": 9, "deprel": "nsubj", "misc": "start_char=1311|end_char=1313", "ner": "O"}, {"id": 8, "text": "ne", "lemma": "ne", "upos": "ADV", "feats": "Polarity=Neg", "head": 9, "deprel": "advmod", "misc": "start_char=1314|end_char=1316", "ner": "O"}, {"id": 9, "text": "veux", "lemma": "vouloir", "upos": "VERB", "feats": "Mood=Ind|Number=Sing|Person=1|Tense=Pres|VerbForm=Fin", "head": 5, "deprel": "ccomp", "misc": "start_char=1317|end_char=1321", "ner": "O"}, {"id": 10, "text": "plus", "lemma": "plus", "upos": "ADV", "head": 11, "deprel": "advmod", "misc": "start_char=1322|end_char=1326", "ner": "O"}, {"id": 11, "text": "cher", "lemma": "cher", "upos": "ADJ", "feats": "Gender=Masc|Number=Sing", "head": 9, "deprel": "xcomp", "misc": "start_char=1327|end_char=1331", "ner": "O"}, {"id": 12, "text": ".", "lemma": ".", "upos": "PUNCT", "head": 3, "deprel": "punct", "misc": "start_char=1331|end_char=1332", "ner": "O"}], [{"id": 1, "text": "Encore", "lemma": "encore", "upos": "ADV", "head": 3, "deprel": "advmod", "misc": "start_char=1333|end_char=1339", "ner": "O"}, {"id": 2, "text": "un", "lemma": "un", "upos": "DET", "feats": "Definite=Ind|Gender=Masc|Number=Sing|PronType=Art", "head": 3, "deprel": "det", "misc": "start_char=1340|end_char=1342", "ner": "O"}, {"id": 3, "text": "tee-shirt", "lemma": "tee-shirt", "upos": "NOUN", "feats": "Gender=Masc|Number=Sing", "head": 0, "deprel": "root", "misc": "start_char=1343|end_char=1352", "ner": "O"}, {"id": 4, "text": "noir", "lemma": "noir", "upos": "ADJ", "feats": "Gender=Masc|Number=Sing", "head": 3, "deprel": "amod", "misc": "start_char=1353|end_char=1357", "ner": "O"}, {"id": 5, "text": "mais", "lemma": "mais", "upos": "CCONJ", "head": 3, "deprel": "cc", "misc": "start_char=1358|end_char=1362", "ner": "O"}, {"id": 6, "text": ".", "lemma": ".", "upos": "PUNCT", "head": 3, "deprel": "punct", "misc": "start_char=1362|end_char=1363", "ner": "O"}], [{"id": 1, "text": "Les", "lemma": "le", "upos": "DET", "feats": "Definite=Def|Gender=Fem|Number=Plur|PronType=Art", "head": 2, "deprel": "det", "misc": "start_char=1364|end_char=1367", "ner": "S-LOC"}, {"id": 2, "text": "choses", "lemma": "chose", "upos": "NOUN", "feats": "Gender=Fem|Number=Plur", "head": 4, "deprel": "nsubj", "misc": "start_char=1368|end_char=1374", "ner": "O"}, {"id": 3, "text": "s'", "lemma": "se", "upos": "PRON", "feats": "Person=3|PronType=Prs", "head": 4, "deprel": "expl:pass", "misc": "start_char=1375|end_char=1377", "ner": "O"}, {"id": 4, "text": "amliorent", "lemma": "amliorer", "upos": "VERB", "feats": "Mood=Ind|Number=Plur|Person=3|Tense=Past|VerbForm=Fin", "head": 0, "deprel": "root", "misc": "start_char=1377|end_char=1386", "ner": "O"}, {"id": 5, "text": "pas", "lemma": "pas", "upos": "ADV", "feats": "Polarity=Neg", "head": 4, "deprel": "advmod", "misc": "start_char=1387|end_char=1390", "ner": "O"}, {"id": 6, "text": ".", "lemma": ".", "upos": "PUNCT", "head": 4, "deprel": "punct", "misc": "start_char=1390|end_char=1391", "ner": "O"}], [{"id": 1, "text": "Pas", "lemma": "pas", "upos": "ADV", "feats": "Polarity=Neg", "head": 3, "deprel": "advmod", "misc": "start_char=1392|end_char=1395", "ner": "O"}, {"id": 2, "text": "le", "lemma": "le", "upos": "DET", "feats": "Definite=Def|Gender=Masc|Number=Sing|PronType=Art", "head": 3, "deprel": "det", "misc": "start_char=1396|end_char=1398", "ner": "O"}, {"id": 3, "text": "choix", "lemma": "choix", "upos": "NOUN", "feats": "Gender=Masc|Number=Sing", "head": 0, "deprel": "root", "misc": "start_char=1399|end_char=1404", "ner": "O"}, {"id": [4, 5], "text": "du", "ner": "O", "misc": "start_char=1405|end_char=1407"}, {"id": 4, "text": "de", "lemma": "de", "upos": "ADP", "head": 6, "deprel": "case"}, {"id": 5, "text": "le", "lemma": "le", "upos": "DET", "feats": "Definite=Def|Gender=Masc|Number=Sing|PronType=Art", "head": 6, "deprel": "det"}, {"id": 6, "text": "changement", "lemma": "changement", "upos": "NOUN", "feats": "Gender=Masc|Number=Sing", "head": 3, "deprel": "nmod", "misc": "start_char=1408|end_char=1418", "ner": "O"}, {"id": [7, 8], "text": "du", "ner": "O", "misc": "start_char=1419|end_char=1421"}, {"id": 7, "text": "de", "lemma": "de", "upos": "ADP", "head": 9, "deprel": "case"}, {"id": 8, "text": "le", "lemma": "le", "upos": "DET", "feats": "Definite=Def|Gender=Masc|Number=Sing|PronType=Art", "head": 9, "deprel": "det"}, {"id": 9, "text": "risque", "lemma": "risque", "upos": "NOUN", "feats": "Gender=Masc|Number=Sing", "head": 6, "deprel": "nmod", "misc": "start_char=1422|end_char=1428", "ner": "O"}, {"id": 10, "text": ".", "lemma": ".", "upos": "PUNCT", "head": 3, "deprel": "punct", "misc": "start_char=1428|end_char=1429", "ner": "O"}], [{"id": 1, "text": "J'", "lemma": "il", "upos": "PRON", "feats": "Number=Sing|Person=1|PronType=Prs", "head": 3, "deprel": "nsubj", "misc": "start_char=1430|end_char=1432", "ner": "O"}, {"id": 2, "text": "ai", "lemma": "avoir", "upos": "AUX", "feats": "Mood=Ind|Number=Sing|Person=1|Tense=Pres|VerbForm=Fin", "head": 3, "deprel": "aux:tense", "misc": "start_char=1432|end_char=1434", "ner": "O"}, {"id": 3, "text": "dcouvert", "lemma": "dcouvrir", "upos": "VERB", "feats": "Gender=Masc|Number=Sing|Tense=Past|VerbForm=Part", "head": 0, "deprel": "root", "misc": "start_char=1435|end_char=1443", "ner": "O"}, {"id": 4, "text": "que", "lemma": "que", "upos": "SCONJ", "head": 8, "deprel": "mark", "misc": "start_char=1444|end_char=1447", "ner": "O"}, {"id": 5, "text": "cela", "lemma": "cela", "upos": "PRON", "feats": "Number=Sing|PronType=Dem", "head": 8, "deprel": "nsubj", "misc": "start_char=1448|end_char=1452", "ner": "O"}, {"id": 6, "text": "ne", "lemma": "ne", "upos": "ADV", "feats": "Polarity=Neg", "head": 8, "deprel": "advmod", "misc": "start_char=1453|end_char=1455", "ner": "O"}, {"id": 7, "text": "le", "lemma": "le", "upos": "PRON", "feats": "Gender=Masc|Number=Sing|Person=3|PronType=Prs", "head": 8, "deprel": "obj", "misc": "start_char=1456|end_char=1458", "ner": "O"}, {"id": 8, "text": "digre", "lemma": "digre", "upos": "VERB", "feats": "Mood=Ind|Number=Sing|Person=3|Tense=Pres|VerbForm=Fin", "head": 3, "deprel": "ccomp", "misc": "start_char=1459|end_char=1464", "ner": "O"}, {"id": 9, "text": ".", "lemma": ".", "upos": "PUNCT", "head": 3, "deprel": "punct", "misc": "start_char=1464|end_char=1465", "ner": "O"}], [{"id": 1, "text": "Depuis", "lemma": "depuis", "upos": "ADP", "head": 2, "deprel": "case", "misc": "start_char=1466|end_char=1472", "ner": "O"}, {"id": 2, "text": "beaucoup", "lemma": "beaucoup", "upos": "ADV", "head": 0, "deprel": "root", "misc": "start_char=1473|end_char=1481", "ner": "O"}, {"id": 3, "text": "de", "lemma": "de", "upos": "ADP", "head": 4, "deprel": "case", "misc": "start_char=1482|end_char=1484", "ner": "O"}, {"id": 4, "text": "moments", "lemma": "moment", "upos": "NOUN", "feats": "Gender=Masc|Number=Plur", "head": 2, "deprel": "obl:arg", "misc": "start_char=1485|end_char=1492", "ner": "O"}, {"id": 5, "text": "arrte", "lemma": "arrte", "upos": "ADJ", "feats": "Gender=Masc|Number=Plur", "head": 4, "deprel": "amod", "misc": "start_char=1493|end_char=1498", "ner": "O"}, {"id": 6, "text": "de", "lemma": "de", "upos": "ADP", "head": 7, "deprel": "mark", "misc": "start_char=1499|end_char=1501", "ner": "O"}, {"id": 7, "text": "faire", "lemma": "faire", "upos": "VERB", "feats": "VerbForm=Inf", "head": 4, "deprel": "acl", "misc": "start_char=1502|end_char=1507", "ner": "O"}, {"id": 8, "text": "des", "lemma": "un", "upos": "DET", "feats": "Definite=Ind|Gender=Masc|Number=Plur|PronType=Art", "head": 10, "deprel": "det", "misc": "start_char=1508|end_char=1511", "ner": "O"}, {"id": 9, "text": "petits", "lemma": "petit", "upos": "ADJ", "feats": "Gender=Masc|Number=Plur", "head": 10, "deprel": "amod", "misc": "start_char=1512|end_char=1518", "ner": "O"}, {"id": 10, "text": "fous", "lemma": "fou", "upos": "NOUN", "feats": "Gender=Masc|Number=Plur", "head": 7, "deprel": "obj", "misc": "start_char=1519|end_char=1523", "ner": "O"}, {"id": 11, "text": ".", "lemma": ".", "upos": "PUNCT", "head": 2, "deprel": "punct", "misc": "start_char=1523|end_char=1524", "ner": "O"}], [{"id": 1, "text": "Depuis", "lemma": "depuis", "upos": "ADP", "head": 3, "deprel": "case", "misc": "start_char=1525|end_char=1531", "ner": "O"}, {"id": 2, "text": "le", "lemma": "le", "upos": "DET", "feats": "Definite=Def|Gender=Masc|Number=Sing|PronType=Art", "head": 3, "deprel": "det", "misc": "start_char=1532|end_char=1534", "ner": "O"}, {"id": 3, "text": "dbut", "lemma": "dbut", "upos": "NOUN", "feats": "Gender=Masc|Number=Sing", "head": 0, "deprel": "root", "misc": "start_char=1535|end_char=1539", "ner": "O"}, {"id": [4, 5], "text": "des", "ner": "O", "misc": "start_char=1540|end_char=1543"}, {"id": 4, "text": "de", "lemma": "de", "upos": "ADP", "head": 6, "deprel": "case"}, {"id": 5, "text": "les", "lemma": "le", "upos": "DET", "feats": "Definite=Def|Gender=Masc|Number=Plur|PronType=Art", "head": 6, "deprel": "det"}, {"id": 6, "text": "jo", "lemma": "jo", "upos": "NOUN", "feats": "Gender=Masc|Number=Plur", "head": 3, "deprel": "nmod", "misc": "start_char=1544|end_char=1546", "ner": "O"}, {"id": 7, "text": "raisonnable", "lemma": "raisonnable", "upos": "ADJ", "feats": "Gender=Masc|Number=Sing", "head": 6, "deprel": "amod", "misc": "start_char=1547|end_char=1558", "ner": "O"}, {"id": 8, "text": "quelques", "lemma": "quelque", "upos": "DET", "feats": "Gender=Fem|Number=Plur", "head": 9, "deprel": "det", "misc": "start_char=1559|end_char=1567", "ner": "O"}, {"id": 9, "text": "conditions", "lemma": "condition", "upos": "NOUN", "feats": "Gender=Fem|Number=Plur", "head": 3, "deprel": "nmod", "misc": "start_char=1568|end_char=1578", "ner": "O"}, {"id": 10, "text": "la", "lemma": "le", "upos": "DET", "feats": "Definite=Def|Gender=Fem|Number=Sing|PronType=Art", "head": 11, "deprel": "det", "misc": "start_char=1580|end_char=1582", "ner": "O"}, {"id": 11, "text": "socit", "lemma": "socit", "upos": "NOUN", "feats": "Gender=Fem|Number=Sing", "head": 9, "deprel": "appos", "misc": "start_char=1583|end_char=1588", "ner": "O"}, {"id": 12, "text": ".", "lemma": ".", "upos": "PUNCT", "head": 9, "deprel": "punct", "misc": "start_char=1588|end_char=1589", "ner": "O"}], [{"id": 1, "text": "Le", "lemma": "le", "upos": "PRON", "feats": "Gender=Masc|Number=Sing|Person=3|PronType=Prs", "head": 3, "deprel": "obj", "misc": "start_char=1590|end_char=1592", "ner": "O"}, {"id": 2, "text": "faire", "lemma": "faire", "upos": "AUX", "feats": "VerbForm=Inf", "head": 3, "deprel": "aux:caus", "misc": "start_char=1593|end_char=1598", "ner": "O"}, {"id": 3, "text": "normal", "lemma": "normal", "upos": "ADJ", "feats": "Gender=Masc|Number=Sing", "head": 0, "deprel": "root", "misc": "start_char=1599|end_char=1605", "ner": "O"}, {"id": 4, "text": ".", "lemma": ".", "upos": "PUNCT", "head": 3, "deprel": "punct", "misc": "start_char=1605|end_char=1606", "ner": "O"}], [{"id": 1, "text": "Alors", "lemma": "alors", "upos": "ADV", "head": 2, "deprel": "advmod", "misc": "start_char=1607|end_char=1612", "ner": "O"}, {"id": 2, "text": "pour", "lemma": "pour", "upos": "ADP", "head": 0, "deprel": "root", "misc": "start_char=1613|end_char=1617", "ner": "O"}, {"id": 3, "text": "ou", "lemma": "ou", "upos": "CCONJ", "head": 2, "deprel": "fixed", "misc": "start_char=1618|end_char=1620", "ner": "O"}, {"id": 4, "text": "contre", "lemma": "contre", "upos": "NOUN", "head": 2, "deprel": "conj", "misc": "start_char=1621|end_char=1627", "ner": "O"}, {"id": 5, "text": ".", "lemma": ".", "upos": "PUNCT", "head": 2, "deprel": "punct", "misc": "start_char=1627|end_char=1628", "ner": "O"}], [{"id": 1, "text": "Ces", "lemma": "ce", "upos": "DET", "feats": "Gender=Masc|Number=Plur|PronType=Dem", "head": 3, "deprel": "det", "misc": "start_char=1629|end_char=1632", "ner": "O"}, {"id": 2, "text": "deux", "lemma": "deux", "upos": "NUM", "head": 3, "deprel": "nummod", "misc": "start_char=1633|end_char=1637", "ner": "O"}, {"id": 3, "text": "frres", "lemma": "frre", "upos": "NOUN", "feats": "Gender=Masc|Number=Plur", "head": 0, "deprel": "root", "misc": "start_char=1638|end_char=1643", "ner": "O"}, {"id": 4, "text": ".", "lemma": ".", "upos": "PUNCT", "head": 3, "deprel": "punct", "misc": "start_char=1643|end_char=1644", "ner": "O"}], [{"id": 1, "text": "16 16", "lemma": "16 16", "upos": "NUM", "head": 2, "deprel": "nummod", "misc": "start_char=1645|end_char=1650", "ner": "O"}, {"id": 2, "text": "dollars", "lemma": "dollar", "upos": "NOUN", "feats": "Gender=Masc|Number=Plur", "head": 0, "deprel": "root", "misc": "start_char=1651|end_char=1658", "ner": "O"}, {"id": 3, "text": "le", "lemma": "le", "upos": "DET", "feats": "Definite=Def|Gender=Masc|Number=Sing|PronType=Art", "head": 4, "deprel": "det", "misc": "start_char=1659|end_char=1661", "ner": "O"}, {"id": 4, "text": "baril", "lemma": "baril", "upos": "NOUN", "feats": "Gender=Masc|Number=Sing", "head": 2, "deprel": "appos", "misc": "start_char=1662|end_char=1667", "ner": "O"}, {"id": 5, "text": ".", "lemma": ".", "upos": "PUNCT", "head": 2, "deprel": "punct", "misc": "start_char=1667|end_char=1668", "ner": "O"}], [{"id": 1, "text": "Mais", "lemma": "mais", "upos": "CCONJ", "head": 4, "deprel": "cc", "misc": "start_char=1669|end_char=1673", "ner": "O"}, {"id": 2, "text": "il", "lemma": "il", "upos": "PRON", "feats": "Gender=Masc|Number=Sing|Person=3|PronType=Prs", "head": 4, "deprel": "nsubj", "misc": "start_char=1674|end_char=1676", "ner": "O"}, {"id": 3, "text": "est", "lemma": "\u00eatre", "upos": "AUX", "feats": "Mood=Ind|Number=Sing|Person=3|Tense=Pres|VerbForm=Fin", "head": 4, "deprel": "cop", "misc": "start_char=1677|end_char=1680", "ner": "O"}, {"id": 4, "text": "bientt", "lemma": "bientt", "upos": "ADJ", "feats": "Gender=Masc|Number=Sing", "head": 0, "deprel": "root", "misc": "start_char=1681|end_char=1687", "ner": "O"}, {"id": 5, "text": ".", "lemma": ".", "upos": "PUNCT", "head": 4, "deprel": "punct", "misc": "start_char=1687|end_char=1688", "ner": "O"}], [{"id": [1, 2], "text": "Au", "ner": "O", "misc": "start_char=1689|end_char=1691"}, {"id": 1, "text": "\u00e0", "lemma": "\u00e0", "upos": "ADP", "head": 6, "deprel": "advmod"}, {"id": 2, "text": "le", "lemma": "le", "upos": "DET", "feats": "Definite=Def|Gender=Masc|Number=Sing|PronType=Art", "head": 1, "deprel": "fixed"}, {"id": 3, "text": "final", "lemma": "final", "upos": "NOUN", "feats": "Gender=Masc|Number=Sing", "head": 1, "deprel": "fixed", "misc": "start_char=1692|end_char=1697", "ner": "O"}, {"id": 4, "text": "d'", "lemma": "de", "upos": "ADP", "head": 6, "deprel": "advmod", "misc": "start_char=1698|end_char=1700", "ner": "O"}, {"id": 5, "text": "abord", "lemma": "abord", "upos": "NOUN", "feats": "Gender=Masc|Number=Sing", "head": 4, "deprel": "fixed", "misc": "start_char=1700|end_char=1705", "ner": "O"}, {"id": 6, "text": "faire", "lemma": "faire", "upos": "VERB", "feats": "VerbForm=Inf", "head": 0, "deprel": "root", "misc": "start_char=1706|end_char=1711", "ner": "O"}, {"id": 7, "text": "des", "lemma": "un", "upos": "DET", "feats": "Definite=Ind|Gender=Masc|Number=Plur|PronType=Art", "head": 8, "deprel": "det", "misc": "start_char=1712|end_char=1715", "ner": "O"}, {"id": 8, "text": "choix", "lemma": "choix", "upos": "NOUN", "feats": "Gender=Masc|Number=Plur", "head": 6, "deprel": "obj", "misc": "start_char=1716|end_char=1721", "ner": "O"}, {"id": 9, "text": "dans", "lemma": "dans", "upos": "ADP", "head": 11, "deprel": "case", "misc": "start_char=1722|end_char=1726", "ner": "O"}, {"id": 10, "text": "la", "lemma": "le", "upos": "DET", "feats": "Definite=Def|Gender=Fem|Number=Sing|PronType=Art", "head": 11, "deprel": "det", "misc": "start_char=1727|end_char=1729", "ner": "O"}, {"id": 11, "text": "vie", "lemma": "vie", "upos": "NOUN", "feats": "Gender=Fem|Number=Sing", "head": 6, "deprel": "obl:mod", "misc": "start_char=1730|end_char=1733", "ner": "O"}, {"id": 12, "text": "pour", "lemma": "pour", "upos": "ADP", "head": 13, "deprel": "mark", "misc": "start_char=1734|end_char=1738", "ner": "O"}, {"id": 13, "text": "prendre", "lemma": "prendre", "upos": "VERB", "feats": "VerbForm=Inf", "head": 6, "deprel": "advcl", "misc": "start_char=1739|end_char=1746", "ner": "O"}, {"id": 14, "text": "une", "lemma": "un", "upos": "DET", "feats": "Definite=Ind|Gender=Fem|Number=Sing|PronType=Art", "head": 15, "deprel": "det", "misc": "start_char=1747|end_char=1750", "ner": "O"}, {"id": 15, "text": "dcision", "lemma": "dcision", "upos": "NOUN", "feats": "Gender=Fem|Number=Sing", "head": 13, "deprel": "obj", "misc": "start_char=1751|end_char=1758", "ner": "O"}, {"id": 16, "text": ".", "lemma": ".", "upos": "PUNCT", "head": 6, "deprel": "punct", "misc": "start_char=1758|end_char=1759", "ner": "O"}], [{"id": 1, "text": "Importante", "lemma": "important", "upos": "ADJ", "feats": "Gender=Fem|Number=Sing", "head": 0, "deprel": "root", "misc": "start_char=1760|end_char=1770", "ner": "O"}, {"id": [2, 3], "text": "du", "ner": "O", "misc": "start_char=1771|end_char=1773"}, {"id": 2, "text": "de", "lemma": "de", "upos": "ADP", "head": 1, "deprel": "advmod"}, {"id": 3, "text": "le", "lemma": "le", "upos": "DET", "feats": "Definite=Def|Gender=Masc|Number=Sing|PronType=Art", "head": 2, "deprel": "fixed"}, {"id": 4, "text": "fait", "lemma": "fait", "upos": "NOUN", "feats": "Gender=Masc|Number=Sing", "head": 2, "deprel": "fixed", "misc": "start_char=1774|end_char=1778", "ner": "O"}, {"id": 5, "text": "d'", "lemma": "de", "upos": "ADP", "head": 8, "deprel": "case", "misc": "start_char=1779|end_char=1781", "ner": "O"}, {"id": 6, "text": "une", "lemma": "un", "upos": "DET", "feats": "Definite=Ind|Gender=Fem|Number=Sing|PronType=Art", "head": 8, "deprel": "det", "misc": "start_char=1781|end_char=1784", "ner": "O"}, {"id": 7, "text": "seule", "lemma": "seul", "upos": "ADJ", "feats": "Gender=Fem|Number=Sing", "head": 8, "deprel": "amod", "misc": "start_char=1785|end_char=1790", "ner": "O"}, {"id": 8, "text": "chose", "lemma": "chose", "upos": "NOUN", "feats": "Gender=Fem|Number=Sing", "head": 2, "deprel": "obl:arg", "misc": "start_char=1791|end_char=1796", "ner": "O"}, {"id": 9, "text": ".", "lemma": ".", "upos": "PUNCT", "head": 1, "deprel": "punct", "misc": "start_char=1796|end_char=1797", "ner": "O"}], [{"id": 1, "text": "Dtermination", "lemma": "Dtermination", "upos": "PROPN", "head": 0, "deprel": "root", "misc": "start_char=1798|end_char=1810", "ner": "S-MISC"}, {"id": 2, "text": ".", "lemma": ".", "upos": "PUNCT", "head": 1, "deprel": "punct", "misc": "start_char=1810|end_char=1811", "ner": "O"}], [{"id": 1, "text": "Le", "lemma": "le", "upos": "DET", "feats": "Definite=Def|Gender=Masc|Number=Sing|PronType=Art", "head": 2, "deprel": "det", "misc": "start_char=1812|end_char=1814", "ner": "B-MISC"}, {"id": 2, "text": "ton", "lemma": "ton", "upos": "NOUN", "feats": "Gender=Masc|Number=Sing", "head": 7, "deprel": "nsubj", "misc": "start_char=1815|end_char=1818", "ner": "E-MISC"}, {"id": 3, "text": "est", "lemma": "\u00eatre", "upos": "AUX", "feats": "Mood=Ind|Number=Sing|Person=3|Tense=Pres|VerbForm=Fin", "head": 7, "deprel": "cop", "misc": "start_char=1819|end_char=1822", "ner": "O"}, {"id": 4, "text": "donn", "lemma": "donn", "upos": "ADV", "head": 7, "deprel": "advmod", "misc": "start_char=1823|end_char=1827", "ner": "O"}, {"id": 5, "text": "absolument", "lemma": "absolument", "upos": "ADV", "head": 7, "deprel": "advmod", "misc": "start_char=1828|end_char=1838", "ner": "O"}, {"id": 6, "text": "pas", "lemma": "pas", "upos": "ADV", "feats": "Polarity=Neg", "head": 7, "deprel": "advmod", "misc": "start_char=1839|end_char=1842", "ner": "O"}, {"id": 7, "text": "bon", "lemma": "bon", "upos": "ADJ", "feats": "Gender=Masc|Number=Sing", "head": 0, "deprel": "root", "misc": "start_char=1843|end_char=1846", "ner": "O"}, {"id": 8, "text": "c'", "lemma": "ce", "upos": "PRON", "feats": "Number=Sing|Person=3|PronType=Dem", "head": 13, "deprel": "nsubj", "misc": "start_char=1847|end_char=1849", "ner": "O"}, {"id": 9, "text": "est", "lemma": "\u00eatre", "upos": "AUX", "feats": "Mood=Ind|Number=Sing|Person=3|Tense=Pres|VerbForm=Fin", "head": 8, "deprel": "fixed", "misc": "start_char=1849|end_char=1852", "ner": "O"}, {"id": 10, "text": "dcid", "lemma": "dcid", "upos": "SCONJ", "head": 13, "deprel": "mark", "misc": "start_char=1853|end_char=1857", "ner": "O"}, {"id": 11, "text": "je", "lemma": "il", "upos": "PRON", "feats": "Number=Sing|Person=1|PronType=Prs", "head": 13, "deprel": "nsubj", "misc": "start_char=1858|end_char=1860", "ner": "O"}, {"id": 12, "text": "me", "lemma": "se", "upos": "PRON", "feats": "Number=Sing|Person=1|PronType=Prs", "head": 13, "deprel": "expl:comp", "misc": "start_char=1861|end_char=1863", "ner": "O"}, {"id": 13, "text": "mets", "lemma": "mettre", "upos": "VERB", "feats": "Mood=Ind|Number=Sing|Person=1|Tense=Pres|VerbForm=Fin", "head": 7, "deprel": "advcl", "misc": "start_char=1864|end_char=1868", "ner": "O"}, {"id": 14, "text": "moi-mme", "lemma": "moi-mme", "upos": "ADV", "head": 13, "deprel": "advmod", "misc": "start_char=1869|end_char=1876", "ner": "O"}, {"id": 15, "text": ".", "lemma": ".", "upos": "PUNCT", "head": 7, "deprel": "punct", "misc": "start_char=1876|end_char=1877", "ner": "O"}], [{"id": 1, "text": "Pas", "lemma": "pas", "upos": "ADV", "feats": "Polarity=Neg", "head": 2, "deprel": "advmod", "misc": "start_char=1878|end_char=1881", "ner": "O"}, {"id": 2, "text": "mal", "lemma": "mal", "upos": "ADV", "head": 0, "deprel": "root", "misc": "start_char=1882|end_char=1885", "ner": "O"}, {"id": 3, "text": ".", "lemma": ".", "upos": "PUNCT", "head": 2, "deprel": "punct", "misc": "start_char=1885|end_char=1886", "ner": "O"}], [{"id": 1, "text": "Pourquoi", "lemma": "pourquoi", "upos": "ADV", "head": 0, "deprel": "root", "misc": "start_char=1887|end_char=1895", "ner": "O"}, {"id": 2, "text": ".", "lemma": ".", "upos": "PUNCT", "head": 1, "deprel": "punct", "misc": "start_char=1895|end_char=1896", "ner": "O"}], [{"id": 1, "text": "Je", "lemma": "il", "upos": "PRON", "feats": "Number=Sing|Person=1|PronType=Prs", "head": 2, "deprel": "nsubj", "misc": "start_char=1897|end_char=1899", "ner": "O"}, {"id": 2, "text": "sais", "lemma": "savoir", "upos": "VERB", "feats": "Mood=Ind|Number=Sing|Person=1|Tense=Pres|VerbForm=Fin", "head": 0, "deprel": "root", "misc": "start_char=1900|end_char=1904", "ner": "O"}, {"id": 3, "text": "pas", "lemma": "pas", "upos": "ADV", "feats": "Polarity=Neg", "head": 2, "deprel": "advmod", "misc": "start_char=1905|end_char=1908", "ner": "O"}, {"id": 4, "text": "comment", "lemma": "comment", "upos": "ADV", "head": 5, "deprel": "advmod", "misc": "start_char=1909|end_char=1916", "ner": "O"}, {"id": 5, "text": "font", "lemma": "faire", "upos": "VERB", "feats": "Mood=Ind|Number=Plur|Person=3|Tense=Pres|VerbForm=Fin", "head": 2, "deprel": "ccomp", "misc": "start_char=1917|end_char=1921", "ner": "O"}, {"id": 6, "text": "les", "lemma": "le", "upos": "DET", "feats": "Definite=Def|Number=Plur|PronType=Art", "head": 7, "deprel": "det", "misc": "start_char=1922|end_char=1925", "ner": "O"}, {"id": 7, "text": "autres", "lemma": "autre", "upos": "PRON", "feats": "Number=Plur", "head": 5, "deprel": "obj", "misc": "start_char=1926|end_char=1932", "ner": "O"}, {"id": 8, "text": ".", "lemma": ".", "upos": "PUNCT", "head": 2, "deprel": "punct", "misc": "start_char=1932|end_char=1933", "ner": "O"}], [{"id": 1, "text": "Or", "lemma": "or", "upos": "CCONJ", "head": 4, "deprel": "cc", "misc": "start_char=1934|end_char=1936", "ner": "S-LOC"}, {"id": 2, "text": "pour", "lemma": "pour", "upos": "ADP", "head": 4, "deprel": "mark", "misc": "start_char=1937|end_char=1941", "ner": "O"}, {"id": 3, "text": "tre", "lemma": "tre", "upos": "AUX", "feats": "VerbForm=Inf", "head": 4, "deprel": "cop", "misc": "start_char=1942|end_char=1945", "ner": "O"}, {"id": 4, "text": "heureux", "lemma": "heureux", "upos": "ADJ", "feats": "Gender=Masc|Number=Sing", "head": 0, "deprel": "root", "misc": "start_char=1946|end_char=1953", "ner": "O"}, {"id": 5, "text": ".", "lemma": ".", "upos": "PUNCT", "head": 4, "deprel": "punct", "misc": "start_char=1953|end_char=1954", "ner": "O"}], [{"id": 1, "text": "Page", "lemma": "Page", "upos": "NOUN", "feats": "Gender=Fem|Number=Sing", "head": 2, "deprel": "nsubj", "misc": "start_char=1955|end_char=1959", "ner": "B-MISC"}, {"id": 2, "text": "facebook", "lemma": "facebookr", "upos": "VERB", "feats": "Mood=Ind|Number=Sing|Person=3|Tense=Pres|VerbForm=Fin", "head": 0, "deprel": "root", "misc": "start_char=1960|end_char=1968", "ner": "E-MISC"}, {"id": 3, "text": "finalement", "lemma": "finalement", "upos": "ADV", "head": 2, "deprel": "advmod", "misc": "start_char=1969|end_char=1979", "ner": "O"}, {"id": 4, "text": "pas", "lemma": "pas", "upos": "ADV", "feats": "Polarity=Neg", "head": 2, "deprel": "advmod", "misc": "start_char=1980|end_char=1983", "ner": "O"}, {"id": 5, "text": "tant", "lemma": "tant", "upos": "ADV", "head": 2, "deprel": "advmod", "misc": "start_char=1984|end_char=1988", "ner": "O"}, {"id": 6, "text": ".", "lemma": ".", "upos": "PUNCT", "head": 2, "deprel": "punct", "misc": "start_char=1988|end_char=1989", "ner": "O"}], [{"id": 1, "text": "Voil", "lemma": "voil", "upos": "INTJ", "head": 5, "deprel": "discourse", "misc": "start_char=1990|end_char=1994", "ner": "S-MISC"}, {"id": 2, "text": "l'", "lemma": "le", "upos": "PRON", "feats": "Number=Sing|Person=3|PronType=Prs", "head": 5, "deprel": "nsubj", "misc": "start_char=1995|end_char=1997", "ner": "O"}, {"id": 3, "text": "t", "lemma": "t", "upos": "AUX", "feats": "Mood=Ind|Number=Sing|Person=3|Tense=Pres|VerbForm=Fin", "head": 5, "deprel": "cop", "misc": "start_char=1997|end_char=1998", "ner": "O"}, {"id": 4, "text": "pas", "lemma": "pas", "upos": "ADV", "feats": "Polarity=Neg", "head": 5, "deprel": "advmod", "misc": "start_char=1999|end_char=2002", "ner": "O"}, {"id": 5, "text": "oblig", "lemma": "oblig", "upos": "ADJ", "feats": "Gender=Masc|Number=Sing", "head": 0, "deprel": "root", "misc": "start_char=2003|end_char=2008", "ner": "O"}, {"id": 6, "text": "de", "lemma": "de", "upos": "ADP", "head": 7, "deprel": "mark", "misc": "start_char=2009|end_char=2011", "ner": "O"}, {"id": 7, "text": "cliquer", "lemma": "cliquer", "upos": "VERB", "feats": "VerbForm=Inf", "head": 5, "deprel": "csubj", "misc": "start_char=2012|end_char=2019", "ner": "O"}, {"id": 8, "text": "sur", "lemma": "sur", "upos": "ADP", "head": 10, "deprel": "mark", "misc": "start_char=2020|end_char=2023", "ner": "O"}, {"id": 9, "text": "j'", "lemma": "il", "upos": "PRON", "feats": "Number=Sing|Person=1|PronType=Prs", "head": 10, "deprel": "nsubj", "misc": "start_char=2024|end_char=2026", "ner": "O"}, {"id": 10, "text": "aime", "lemma": "aimer", "upos": "VERB", "feats": "Mood=Ind|Number=Sing|Person=1|Tense=Pres|VerbForm=Fin", "head": 7, "deprel": "advcl", "misc": "start_char=2026|end_char=2030", "ner": "O"}, {"id": 11, "text": "sur", "lemma": "sur", "upos": "ADP", "head": 13, "deprel": "case", "misc": "start_char=2031|end_char=2034", "ner": "O"}, {"id": 12, "text": "la", "lemma": "le", "upos": "DET", "feats": "Definite=Def|Gender=Fem|Number=Sing|PronType=Art", "head": 13, "deprel": "det", "misc": "start_char=2035|end_char=2037", "ner": "O"}, {"id": 13, "text": "page", "lemma": "page", "upos": "NOUN", "feats": "Gender=Fem|Number=Sing", "head": 10, "deprel": "obl", "misc": "start_char=2038|end_char=2042", "ner": "O"}, {"id": 14, "text": ".", "lemma": ".", "upos": "PUNCT", "head": 5, "deprel": "punct", "misc": "start_char=2042|end_char=2043", "ner": "O"}], [{"id": 1, "text": "Et", "lemma": "et", "upos": "CCONJ", "head": 4, "deprel": "cc", "misc": "start_char=2044|end_char=2046", "ner": "O"}, {"id": 2, "text": "si", "lemma": "si", "upos": "SCONJ", "head": 4, "deprel": "mark", "misc": "start_char=2047|end_char=2049", "ner": "O"}, {"id": 3, "text": "vous", "lemma": "il", "upos": "PRON", "feats": "Number=Plur|Person=2|PronType=Prs", "head": 4, "deprel": "nsubj", "misc": "start_char=2050|end_char=2054", "ner": "O"}, {"id": 4, "text": "dpassez", "lemma": "dpasser", "upos": "VERB", "feats": "Mood=Ind|Number=Plur|Person=2|Tense=Pres|VerbForm=Fin", "head": 0, "deprel": "root", "misc": "start_char=2055|end_char=2062", "ner": "O"}, {"id": 5, "text": "pas", "lemma": "pas", "upos": "ADV", "feats": "Polarity=Neg", "head": 4, "deprel": "advmod", "misc": "start_char=2063|end_char=2066", "ner": "O"}, {"id": 6, "text": "d'", "lemma": "un", "upos": "DET", "feats": "Definite=Ind|Gender=Masc|Number=Sing|PronType=Art", "head": 7, "deprel": "det", "misc": "start_char=2067|end_char=2069", "ner": "O"}, {"id": 7, "text": "annuaire", "lemma": "annuaire", "upos": "NOUN", "feats": "Gender=Masc|Number=Sing", "head": 4, "deprel": "obj", "misc": "start_char=2069|end_char=2077", "ner": "O"}, {"id": 8, "text": ".", "lemma": ".", "upos": "PUNCT", "head": 4, "deprel": "punct", "misc": "start_char=2077|end_char=2078", "ner": "O"}]]